{
    "type": "layer",
    "arcgis_connection_file": "gisc_carto.sde",
    "arcgis_dataset": "gisc_carto.UGISC.Cartografia_Base",
    "arcgis_layer": "gisc_carto.UGISC.Curso_Agua",
    "arcgis_attachments": false,
    "where_clause": null,
    "pgsql_schema": "cartografia",
    "pgsql_table": "curso_agua",
    "pgsql_create_table_script": "curso_agua.sql",
    "fields": [
        [
            "OBJECTID",
            "objectid",
            "objectid"
        ],
        [
            "ID_CURSO",
            "id_curso",
            "numeric"
        ],
        [
            "CODIGO",
            "codigo",
            "text"
        ],
        [
            "NOME",
            "nome",
            "text"
        ],
        [
            "REGIME",
            "regime",
            "text"
        ],
        [
            "Enabled",
            "enabled",
            "bool"
        ],
        [
            "DATA",
            "data",
            "date"
        ],
        [
            "SHAPE@WKT",
            "geometry",
            "geometry"
        ]
    ]
}